sphinx_xournal/__init__.py
sphinx_xournal/convert.py
sphinx_xournal/directives.py
sphinx_xournal/exceptions.py
sphinx_xournal/main.py
sphinx_xournal/xournal.css
sphinx_xournal-0.1.2.dist-info/LICENSE
sphinx_xournal-0.1.2.dist-info/WHEEL
sphinx_xournal-0.1.2.dist-info/METADATA
sphinx_xournal-0.1.2.dist-info/RECORD
